[
    {
        "title": "Программист",
        "link": "http://example.com/job1",
        "salary": 150000,
        "description": "Разработка приложений на Python",
        "requirements": "Опыт работы 2 года"
    },
    {
        "title": "Дизайнер",
        "link": "http://example.com/job3",
        "salary": 100000,
        "description": "Дизайн интерфейсов",
        "requirements": "Навыки работы с Figma"
    },
    {
        "title": "Дизайнер",
        "link": "http://example.com/job3",
        "salary": 55000,
        "description": "Дизайн интерфейсов",
        "requirements": "Навыки работы с Figma"
    },
    {
        "title": "Программист",
        "link": "http://example.com/job1",
        "salary": 60000,
        "description": "Разработка приложений на Python",
        "requirements": "Опыт работы 2 года"
    },
    {
        "title": "Дизайнер",
        "link": "http://example.com/job3",
        "salary": 30000,
        "description": "Дизайн интерфейсов",
        "requirements": "Навыки работы с Figma"
    }
]